PreLab1/source.v
`timescale 1ns / 1ns
module source(cc, aa, bb);

input wire [1:0]aa; // 2 bit
input wire [1:0] bb; // 2 bit
output wire [1:0] cc; // 2 bit


wire term1_and;
wire term2_and;
wire term3_and;

wire term4_and;
wire term5_and;
wire term6_and;



and(term1_and, !aa[0], !aa[1], bb[0], bb[1]);
and(term2_and, !aa[0], aa[1], bb[0]);
and(term3_and, aa[0], !bb[0]);

or(cc[0], term1_and, term2_and,term3_and);


and(term4_and, !aa[0], !aa[1], bb[0], bb[1]);
and(term5_and, !aa[0], aa[1]);
and(term6_and, aa[0], bb[0]);

or(cc[1], term4_and, term5_and,term6_and);

endmodule

PreLab1/testbench.v
`timescale 1ns / 1ns
module testbench();

reg [1:0] aa;
reg [1:0] bb;
wire [1:0] cc;

source s0(cc, aa, bb);

initial begin
    $dumpfile("TimingDiagram.vcd");
    $dumpvars(0, cc, aa, bb);

	aa = 2'b00;
	bb = 2'b00;
	#20;
	aa = 2'b00;
	bb = 2'b01;
	#20;
	aa = 2'b00;
	bb = 2'b10;
	#20;
	aa = 2'b00;
	bb = 2'b11;
	#20;
	
	aa = 2'b01;
	bb = 2'b00;
	#20;
	aa = 2'b01;
	bb = 2'b01;
	#20;
	aa = 2'b01;
	bb = 2'b10;
	#20;
	aa = 2'b01;
	bb = 2'b11;
	#20;
	
	aa = 2'b10;
	bb = 2'b00;
	#20;
	aa = 2'b10;
	bb = 2'b01;
	#20;
	aa = 2'b10;
	bb = 2'b10;
	#20;
	aa = 2'b10;
	bb = 2'b11;
	#20;
	
	aa = 2'b11;
	bb = 2'b00;
	#20;
	aa = 2'b11;
	bb = 2'b01;
	#20;
	aa = 2'b11;
	bb = 2'b10;
	#20;
	aa = 2'b11;
	bb = 2'b11;
	#20;
	
    $finish;
end

endmodule

PreLab1/TimingDiagram.vcd
$date
	Thu Mar 30 23:22:39 2023
$end
$version
	Icarus Verilog
$end
$timescale
	1ns
$end
$scope module testbench $end
$var wire 2 ! cc [1:0] $end
$upscope $end
$scope module testbench $end
$var reg 2 " aa [1:0] $end
$upscope $end
$scope module testbench $end
$var reg 2 # bb [1:0] $end
$upscope $end
$enddefinitions $end
$comment Show the parameter values. $end
$dumpall
$end
#0
$dumpvars
b0 #
b0 "
b0 !
$end
#20
b1 #
#40
b10 #
#60
b11 !
b11 #
#80
b1 !
b0 #
b1 "
#100
b10 !
b1 #
#120
b1 !
b10 #
#140
b10 !
b11 #
#160
b0 #
b10 "
#180
b11 !
b1 #
#200
b10 !
b10 #
#220
b11 !
b11 #
#240
b1 !
b0 #
b11 "
#260
b10 !
b1 #
#280
b1 !
b10 #
#300
b10 !
b11 #
