Prelab2/source.v
`timescale 1ns / 1ns

module encoder(y, x);

  output reg [2:0] y;
  input wire [6:0] x;

  always @(x) begin
    y = x[6] + x[5] + x[4] + x[3] + x[2] + x[1] + x[0];
  end
  
endmodule


module mux(z, y, s);

  output reg z;
  input wire [2:0] y;
  input wire [1:0] s;

  always @(y,s) begin
    case(y[0] + y[1] + y[2])
      2'b00: z = (s == 2'b00) ? 1 : 0;
      2'b01: z = (s == 2'b01) ? 1 : 0;
      2'b10: z = (s == 2'b10) ? 1 : 0;
      2'b11: z = (s == 2'b11) ? 1 : 0;
    endcase
  end
  
endmodule

Prelab2/testbenchMux.v
`timescale 1ns / 1ns
module testbench();

reg [2:0] yy;
reg [1:0] ss;
wire zz;

mux m(zz, yy, ss);

initial begin
    $dumpfile("TimingDiagramMux.vcd");
    $dumpvars(0,zz, yy, ss);
    	
    yy = 3'b000;
    ss = 2'b00;
    #20;
   
    yy = 3'b010;
    ss = 2'b00;
    #20;

    yy = 3'b010;
    ss = 2'b01;
    #20;

    yy = 3'b011;
    ss = 2'b01;
    #20;

    yy = 3'b011;
    ss = 2'b10;
    #20;   

    yy = 3'b000;
    ss = 2'b10;
    #20;

    yy = 3'b111;
    ss = 2'b11;
    #20;

    yy = 3'b100;
    ss = 2'b11;
    #20;

    $finish;
end

endmodule

Prelab2/TimingDiagramMux.vcd
$date
	Thu Apr 13 18:01:31 2023
$end
$version
	Icarus Verilog
$end
$timescale
	1ns
$end
$scope module testbench $end
$var wire 1 ! zz $end
$upscope $end
$scope module testbench $end
$var reg 3 " yy [2:0] $end
$upscope $end
$scope module testbench $end
$var reg 2 # ss [1:0] $end
$upscope $end
$enddefinitions $end
$comment Show the parameter values. $end
$dumpall
$end
#0
$dumpvars
b0 #
b0 "
1!
$end
#20
0!
b10 "
#40
1!
b1 #
#60
0!
b11 "
#80
1!
b10 #
#100
0!
b0 "
#120
1!
b11 #
b111 "
#140
0!
b100 "
